streamxfer/__init__.py
streamxfer/cmd.py
streamxfer/compress.py
streamxfer/format.py
streamxfer/log.py
streamxfer/mssql.py
streamxfer/sink.py
streamxfer/typing.py
streamxfer/utils.py
streamxfer/cli/__init__.py
streamxfer/cli/main.py
streamxfer/cli/mssql_escape.py
streamxfer-0.0.2.dist-info/LICENSE
streamxfer-0.0.2.dist-info/METADATA
streamxfer-0.0.2.dist-info/WHEEL
streamxfer-0.0.2.dist-info/entry_points.txt
streamxfer-0.0.2.dist-info/top_level.txt
streamxfer-0.0.2.dist-info/RECORD
