Metadata-Version: 2.1
Name: streamxfer
Version: 0.0.2
Summary: StreamXfer is a powerful tool for streaming data from SQL Server to local or object storage(S3) for seamless transfer using UNIX pipe, supporting various general data formats(CSV, TSV, JSON).
Home-page: UNKNOWN
License: UNKNOWN
Platform: UNKNOWN
Requires-Python: >=3.9
License-File: LICENSE
Requires-Dist: pymssql ~=2.3.0
Requires-Dist: loguru ~=0.7.0
Requires-Dist: click ~=8.1.3
Requires-Dist: psutil ~=5.9.5
Requires-Dist: orjson ~=3.8.10
